{
  "CardId": "11",
  "CardName": "henchmen_goons",
  "CardDisplayName": "Goons",
  "CardDisplayNameFont": 32,
  "CardDisplayNameSub": "Henchmen",
  "CardDisplayNameSubFont": 22,
  "TemplateId": 13,
  "PowerPrimary": "",
  "PowerSecondary": "",
  "AttributeCost": "",
  "AttributeAttack": "",
  "AttributeRecruit": "",
  "AttributePiercing": "",
  "AttributeAttackDefense": "3+",
  "AttributeVictoryPoints": 5,
  "CardText": "<k>Fight: <k>+1<ATTACK> foreach other <k>Henchmen in the city.",
  "CardTextFont": 22,
  "NumberInDeck": 10,
  "ArtWorkFile": "mrs_deadpool.jpg",
  "ExportedCardFile": "all_new_spider_man_2099_hero_common_11.png",
  "DeckId": 2,
  "TeamIconId": -1,
  "Team": "",
  "PowerPrimaryIconId": -1,
  "PowerSecondaryIconId": -1
}
